ood_detection/__init__.py
ood_detection/_modidx.py
ood_detection/core.py
ood_detection-0.0.9.dist-info/LICENSE
ood_detection-0.0.9.dist-info/METADATA
ood_detection-0.0.9.dist-info/WHEEL
ood_detection-0.0.9.dist-info/entry_points.txt
ood_detection-0.0.9.dist-info/top_level.txt
ood_detection-0.0.9.dist-info/RECORD
