Metadata-Version: 2.1
Name: ood-detection
Version: 0.0.9
Summary: OOD Detection Library built using nbdev
Home-page: https://github.com/yashwiai/ood_detection
Author: Yash Khandelwal
Author-email: yash@wadhwaniai.org
License: Apache Software License 2.0
Keywords: nbdev jupyter notebook python
Classifier: Development Status :: 4 - Beta
Classifier: Intended Audience :: Developers
Classifier: Natural Language :: English
Classifier: Programming Language :: Python :: 3.7
Classifier: Programming Language :: Python :: 3.8
Classifier: Programming Language :: Python :: 3.9
Classifier: Programming Language :: Python :: 3.10
Classifier: License :: OSI Approved :: Apache Software License
Requires-Python: >=3.7
License-File: LICENSE
Requires-Dist: numpy
Requires-Dist: matplotlib
Requires-Dist: sklearn
Requires-Dist: tqdm
Provides-Extra: dev
